LICENSE.txt
README.rst
setup.py
luawhitelist/__init__.py
luawhitelist/bot_disnake.py
luawhitelist/luawl.py
luawhitelist.egg-info/PKG-INFO
luawhitelist.egg-info/SOURCES.txt
luawhitelist.egg-info/dependency_links.txt
luawhitelist.egg-info/requires.txt
luawhitelist.egg-info/top_level.txt