Metadata-Version: 2.1
Name: luawhitelist
Version: 0.54
Summary: pip install luawhitelist
Home-page: UNKNOWN
Author: MaGiXx
Author-email: email@example.com
License: MIT
Keywords: Whitelist for script
Platform: UNKNOWN
License-File: LICENSE.txt
